{
    "Northern Mockingbird": {
        "Adult": {
            "link": [
                "https://www.allaboutbirds.org/guide/assets/photo/63743751-720px.jpg",
                " https://www.allaboutbirds.org/guide/assets/photo/63743751-720px.jpg",
                " https://www.allaboutbirds.org/guide/assets/photo/63743751-1280px.jpg"
            ],
            "description": "Northern Mockingbirds are lankier than Sage Thrashers, with a longer tail and a slightly shorter bill. They have clean whitish underparts unlike Sage Thrashers, which have streaked underparts."
        }
    },
    "Bendire's Thrasher": {
        "Adult": {
            "link": [
                "https://www.allaboutbirds.org/guide/assets/photo/40247581-720px.jpg",
                " https://www.allaboutbirds.org/guide/assets/photo/40247581-1280px.jpg",
                " https://www.allaboutbirds.org/guide/assets/photo/40247581-720px.jpg"
            ],
            "description": "Bendire's Thrashers have longer tails than Sage Thrashers, with a longer and more curved bill. They also have faint spotting on the breast while Sage has a streaked breast and flanks."
        }
    },
    "Curve-billed Thrasher": {
        "Adult/immature": {
            "link": [
                "https://www.allaboutbirds.org/guide/assets/photo/67456841-720px.jpg",
                " https://www.allaboutbirds.org/guide/assets/photo/67456841-1280px.jpg",
                " https://www.allaboutbirds.org/guide/assets/photo/67456841-720px.jpg"
            ],
            "description": "Curve-billed Thrashers are larger than Sage Thrashers and have a longer, curved bill compared with the short, straight bill of Sage Thrashers."
        }
    }
}