{
    "Adult": {
        "link": [
            [
                " https://www.allaboutbirds.org/guide/assets/photo/304470861-480px.jpg",
                " https://www.allaboutbirds.org/guide/assets/photo/304470861-720px.jpg",
                "https://www.allaboutbirds.org/guide/assets/photo/304470861-480px.jpg"
            ],
            [
                " https://www.allaboutbirds.org/guide/assets/photo/304471161-720px.jpg",
                "https://www.allaboutbirds.org/guide/assets/photo/304471161-480px.jpg",
                " https://www.allaboutbirds.org/guide/assets/photo/304471161-480px.jpg"
            ],
            [
                " https://www.allaboutbirds.org/guide/assets/photo/59867281-720px.jpg",
                "https://www.allaboutbirds.org/guide/assets/photo/59867281-480px.jpg",
                " https://www.allaboutbirds.org/guide/assets/photo/59867281-480px.jpg"
            ],
            [
                " https://www.allaboutbirds.org/guide/assets/photo/59867261-480px.jpg",
                " https://www.allaboutbirds.org/guide/assets/photo/59867261-720px.jpg",
                "https://www.allaboutbirds.org/guide/assets/photo/59867261-480px.jpg"
            ],
            [
                " https://www.allaboutbirds.org/guide/assets/videoThumbs/446569-480px.jpg",
                " https://www.allaboutbirds.org/guide/assets/videoThumbs/446569-720px.jpg",
                "https://www.allaboutbirds.org/guide/assets/videoThumbs/446569-480px.jpg"
            ],
            [
                "https://www.allaboutbirds.org/guide/assets/photo/304471261-480px.jpg",
                " https://www.allaboutbirds.org/guide/assets/photo/304471261-720px.jpg",
                " https://www.allaboutbirds.org/guide/assets/photo/304471261-480px.jpg"
            ],
            [
                " https://www.allaboutbirds.org/guide/assets/photo/59867251-720px.jpg",
                "https://www.allaboutbirds.org/guide/assets/photo/59867251-480px.jpg",
                " https://www.allaboutbirds.org/guide/assets/photo/59867251-480px.jpg"
            ],
            [
                " https://www.allaboutbirds.org/guide/assets/videoThumbs/475332-720px.jpg",
                "https://www.allaboutbirds.org/guide/assets/videoThumbs/475332-480px.jpg",
                " https://www.allaboutbirds.org/guide/assets/videoThumbs/475332-480px.jpg"
            ],
            [
                "https://www.allaboutbirds.org/guide/assets/photo/59867291-480px.jpg",
                " https://www.allaboutbirds.org/guide/assets/photo/59867291-480px.jpg",
                " https://www.allaboutbirds.org/guide/assets/photo/59867291-720px.jpg"
            ],
            [
                " https://www.allaboutbirds.org/guide/assets/videoThumbs/442613-480px.jpg",
                " https://www.allaboutbirds.org/guide/assets/videoThumbs/442613-720px.jpg",
                "https://www.allaboutbirds.org/guide/assets/videoThumbs/442613-480px.jpg"
            ],
            [
                "https://www.allaboutbirds.org/guide/assets/photo/59867301-480px.jpg",
                " https://www.allaboutbirds.org/guide/assets/photo/59867301-720px.jpg",
                " https://www.allaboutbirds.org/guide/assets/photo/59867301-480px.jpg"
            ]
        ],
        "description": [
            "Reddish brown upperparts contrast with buffy underparts and white throat and eyebrow. Wings and tail have bold darker barring, and bill is long and thin.",
            "Individuals from southern Texas and northeastern Mexico are boldly barred on the wings and tail, and have faint barring on flanks and back.",
            "The loud, cheerful song is often heard before the bird is seen.",
            "Individuals often hold their tails cocked, emphasizing the black barring.",
            "Forages fairly low in thick tangles of shrubs and vines; also on the ground.",
            "",
            "Individuals often perch bent over, holding their tails cocked.",
            "Note long, curved bill, strong white eyebrow stripe, and rich cinnamon underparts. Often holds tail cocked upward.",
            "Visits feeders, especially during the colder months.",
            "Amount of cinnamon on underparts varies; some individuals are pale, especially toward the throat.",
            "Found in dense woodlands and shrubby habitats."
        ]
    },
    "Male": {
        "link": [
            [
                " https://www.allaboutbirds.org/guide/assets/videoThumbs/471513-720px.jpg",
                " https://www.allaboutbirds.org/guide/assets/videoThumbs/471513-480px.jpg",
                "https://www.allaboutbirds.org/guide/assets/videoThumbs/471513-480px.jpg"
            ]
        ],
        "description": [
            "Males sing a series of several quick, whistled notes, repeated a few times. The notes usually sound three-parted, as in \"tea-kettle-tea-kettle\" or \"germany-germany.\""
        ]
    },
    "Adult (White-browed)": {
        "link": [
            [
                " https://www.allaboutbirds.org/guide/assets/photo/215382611-480px.jpg",
                " https://www.allaboutbirds.org/guide/assets/photo/215382611-720px.jpg",
                "https://www.allaboutbirds.org/guide/assets/photo/215382611-480px.jpg"
            ],
            [
                " https://www.allaboutbirds.org/guide/assets/photo/215382641-720px.jpg",
                " https://www.allaboutbirds.org/guide/assets/photo/215382641-480px.jpg",
                "https://www.allaboutbirds.org/guide/assets/photo/215382641-480px.jpg"
            ]
        ],
        "description": [
            "Individuals from southern Mexico and Central America are dingy white below with cold brown upperparts.",
            ""
        ]
    }
}