{
    "Greater Yellowlegs": {
        "Breeding adult": {
            "link": [
                " https://www.allaboutbirds.org/guide/assets/photo/64836521-1280px.jpg",
                "https://www.allaboutbirds.org/guide/assets/photo/64836521-720px.jpg",
                " https://www.allaboutbirds.org/guide/assets/photo/64836521-720px.jpg"
            ],
            "description": "Greater Yellowlegs are smaller than Willets, with a more slender bill and bright yellow legs (Willets have grayish legs)."
        }
    },
    "American Avocet": {
        "Breeding adult": {
            "link": [
                "https://www.allaboutbirds.org/guide/assets/photo/64807071-720px.jpg",
                " https://www.allaboutbirds.org/guide/assets/photo/64807071-1280px.jpg",
                " https://www.allaboutbirds.org/guide/assets/photo/64807071-720px.jpg"
            ],
            "description": "American Avocets are slimmer and more boldly marked than Willets, with a much thinner, upturned bill. In flight, the white stripe on an avocet\u2019s wing does not come all the way to the tip as it does on Willets."
        }
    },
    "Marbled Godwit": {
        "Breeding adult": {
            "link": [
                "https://www.allaboutbirds.org/guide/assets/photo/64811431-720px.jpg",
                " https://www.allaboutbirds.org/guide/assets/photo/64811431-1280px.jpg",
                " https://www.allaboutbirds.org/guide/assets/photo/64811431-720px.jpg"
            ],
            "description": "Marbled Godwits are buffier, almost cinnamon-colored unlike the grayish Willet. Their bills are even longer than the Willets\u2019 bill (at least twice the length of the head), reddish at the base, and turned slightly upward at the end."
        }
    },
    "Whimbrel": {
        "Adult (Hudsonian)": {
            "link": [
                "https://www.allaboutbirds.org/guide/assets/photo/64810251-720px.jpg",
                " https://www.allaboutbirds.org/guide/assets/photo/64810251-720px.jpg",
                " https://www.allaboutbirds.org/guide/assets/photo/64810251-1280px.jpg"
            ],
            "description": "Whimbrels are browner than Willets, with a clearly downcurved bill and a striped head, whereas Willets have a straight bill and a plain head."
        }
    }
}