{
    "Sedge Wren": {
        "Unknown Type": {
            "link": [
                " https://www.allaboutbirds.org/guide/assets/photo/71006031-1280px.jpg",
                "https://www.allaboutbirds.org/guide/assets/photo/71006031-720px.jpg",
                " https://www.allaboutbirds.org/guide/assets/photo/71006031-720px.jpg"
            ],
            "description": "Sedge Wrens have a streaked crown and heavy barring on the shoulders unlike Marsh Wrens, which have an unstreaked crown and unstreaked shoulders."
        }
    },
    "House Wren": {
        "Unknown Type": {
            "link": [
                "https://www.allaboutbirds.org/guide/assets/photo/59860711-720px.jpg",
                " https://www.allaboutbirds.org/guide/assets/photo/59860711-720px.jpg",
                " https://www.allaboutbirds.org/guide/assets/photo/59860711-1280px.jpg"
            ],
            "description": "House Wrens are more likely encountered around human habitations, places where Marsh Wrens are not likely to be found. House Wrens also lack the Marsh Wren's dark back streaking."
        }
    },
    "Pacific Wren": {
        "Unknown Type": {
            "link": [
                " https://www.allaboutbirds.org/guide/assets/photo/68036701-1280px.jpg",
                " https://www.allaboutbirds.org/guide/assets/photo/68036701-720px.jpg",
                "https://www.allaboutbirds.org/guide/assets/photo/68036701-720px.jpg"
            ],
            "description": "Pacific Wrens have a shorter tail and lack the Marsh Wren's dark back streaking. They also occur in different habitats; Pacific in forested areas and Marsh Wrens in wetland areas."
        }
    },
    "Winter Wren": {
        "Unknown Type": {
            "link": [
                " https://www.allaboutbirds.org/guide/assets/photo/68035621-720px.jpg",
                "https://www.allaboutbirds.org/guide/assets/photo/68035621-720px.jpg",
                " https://www.allaboutbirds.org/guide/assets/photo/68035621-1280px.jpg"
            ],
            "description": "Winter Wrens have a shorter tail and lack the Marsh Wren's dark back streaking. They also occur in different habitats; Winter in forested areas and Marsh Wrens in wetland areas."
        }
    }
}