{
    "Downy Woodpecker": {
        "Male (Eastern)": {
            "link": [
                " https://www.allaboutbirds.org/guide/assets/photo/60397941-1280px.jpg",
                "https://www.allaboutbirds.org/guide/assets/photo/60397941-720px.jpg",
                " https://www.allaboutbirds.org/guide/assets/photo/60397941-720px.jpg"
            ],
            "description": "Downy Woodpeckers are smaller with a smaller bill than Hairy Woodpeckers. The white outer tail feathers are spotted on Downy, but unmarked on Hairy."
        }
    },
    "Ladder-backed Woodpecker": {
        "Male": {
            "link": [
                "https://www.allaboutbirds.org/guide/assets/photo/65054631-720px.jpg",
                " https://www.allaboutbirds.org/guide/assets/photo/65054631-1280px.jpg",
                " https://www.allaboutbirds.org/guide/assets/photo/65054631-720px.jpg"
            ],
            "description": "Ladder-backed Woodpeckers have a black-and-white-barred back unlike Hairy Woodpeckers, which have a white patch down the center of the back."
        }
    },
    "Nuttall's Woodpecker": {
        "Male": {
            "link": [
                " https://www.allaboutbirds.org/guide/assets/photo/68929651-720px.jpg",
                " https://www.allaboutbirds.org/guide/assets/photo/68929651-1280px.jpg",
                "https://www.allaboutbirds.org/guide/assets/photo/68929651-720px.jpg"
            ],
            "description": "Nuttall's Woodpeckers have narrow horizontal bars on the back that Hairy Woodpeckers don't have."
        }
    },
    "American Three-toed Woodpecker": {
        "Adult male": {
            "link": [
                " https://www.allaboutbirds.org/guide/assets/photo/37591201-720px.jpg",
                " https://www.allaboutbirds.org/guide/assets/photo/37591201-1280px.jpg",
                "https://www.allaboutbirds.org/guide/assets/photo/37591201-720px.jpg"
            ],
            "description": "American Three-toed Woodpeckers have finely barred sides, whereas Hairy Woodpeckers have clean white sides. They also have thinner facial stripes than Hairy Woodpeckers, and male Three-toeds have a yellow, not red, crown patch."
        }
    },
    "Yellow-bellied Sapsucker": {
        "Male": {
            "link": [
                " https://www.allaboutbirds.org/guide/assets/photo/65051951-1280px.jpg",
                " https://www.allaboutbirds.org/guide/assets/photo/65051951-720px.jpg",
                "https://www.allaboutbirds.org/guide/assets/photo/65051951-720px.jpg"
            ],
            "description": "Sapsuckers have a white wing patch that Hairy Woodpeckers don't have."
        }
    }
}