{
    "Adult": {
        "link": [
            [
                " https://www.allaboutbirds.org/guide/assets/photo/301564811-480px.jpg",
                "https://www.allaboutbirds.org/guide/assets/photo/301564811-480px.jpg",
                " https://www.allaboutbirds.org/guide/assets/photo/301564811-720px.jpg"
            ],
            [
                "https://www.allaboutbirds.org/guide/assets/videoThumbs/483107-480px.jpg",
                " https://www.allaboutbirds.org/guide/assets/videoThumbs/483107-720px.jpg",
                " https://www.allaboutbirds.org/guide/assets/videoThumbs/483107-480px.jpg"
            ],
            [
                " https://www.allaboutbirds.org/guide/assets/photo/64829091-720px.jpg",
                "https://www.allaboutbirds.org/guide/assets/photo/64829091-480px.jpg",
                " https://www.allaboutbirds.org/guide/assets/photo/64829091-480px.jpg"
            ],
            [
                "https://www.allaboutbirds.org/guide/assets/photo/301565371-480px.jpg",
                " https://www.allaboutbirds.org/guide/assets/photo/301565371-480px.jpg",
                " https://www.allaboutbirds.org/guide/assets/photo/301565371-720px.jpg"
            ],
            [
                "https://www.allaboutbirds.org/guide/assets/photo/64829101-480px.jpg",
                " https://www.allaboutbirds.org/guide/assets/photo/64829101-480px.jpg",
                " https://www.allaboutbirds.org/guide/assets/photo/64829101-720px.jpg"
            ]
        ],
        "description": [
            "Medium-sized pudgy shorebird with short, stocky legs. Intricately patterned with 3 long buffy streaks down the back and a striped head.",
            "Round-bodied shorebird of wet fields. In breeding season, often perches on fence posts to call.",
            "Medium-sized chunky shorebird with a long bill. Note white belly, barred flanks, and dark underwings.",
            "Long-billed shorebird of inland wetlands. Usually found foraging on the ground, but also perches on posts or stumps.",
            "Pudgy shorebird with a long bill and short tail. Note barring on the sides and 3 buffy streaks down the back."
        ]
    },
    "Adult male": {
        "link": [
            [
                " https://www.allaboutbirds.org/guide/assets/photo/301565511-480px.jpg",
                " https://www.allaboutbirds.org/guide/assets/photo/301565511-720px.jpg",
                "https://www.allaboutbirds.org/guide/assets/photo/301565511-480px.jpg"
            ]
        ],
        "description": [
            "Displaying males make a curious whistling noise (\u201cwinnowing\u201d), created by air passing over modified outer tail feathers."
        ]
    },
    "Adult (with Long-billed Dowitcher)": {
        "link": [
            [
                " https://www.allaboutbirds.org/guide/assets/photo/64829081-720px.jpg",
                "https://www.allaboutbirds.org/guide/assets/photo/64829081-480px.jpg",
                " https://www.allaboutbirds.org/guide/assets/photo/64829081-480px.jpg"
            ]
        ],
        "description": [
            "Smaller than a Long-billed Dowitcher (left) with shorter legs and a pudgier body. Note buffy streaks down the back and striped head."
        ]
    },
    "Habitat": {
        "link": [
            [
                " https://www.allaboutbirds.org/guide/assets/photo/301565461-720px.jpg",
                " https://www.allaboutbirds.org/guide/assets/photo/301565461-480px.jpg",
                "https://www.allaboutbirds.org/guide/assets/photo/301565461-480px.jpg"
            ]
        ],
        "description": [
            "Found in muddy pond edges, damp fields, and other wet, open habitats often with thick, low vegetation where these well-camouflaged birds can quickly disappear."
        ]
    }
}